mainmodule/__init__.py
mainmodule/add.py
mainmodule/subtract.py
mainmodule/submodule/__init__.py
mainmodule/submodule/divide.py
mainmodule/submodule/multiply.py
mainmodule-0.0.3.dist-info/METADATA
mainmodule-0.0.3.dist-info/WHEEL
mainmodule-0.0.3.dist-info/top_level.txt
mainmodule-0.0.3.dist-info/RECORD
