Metadata-Version: 2.1
Name: mainmodule
Version: 0.0.3
Summary: This is my first package that will be uploaded on pip
Home-page: UNKNOWN
Author: amit
Author-email: fulldev101@gmail.com
License: UNKNOWN
Keywords: amit,amit-package-tutorial,tutorial
Platform: UNKNOWN
Classifier: Development Status :: 3 - Alpha
Classifier: Intended Audience :: Education
Classifier: Programming Language :: Python :: 2
Classifier: Programming Language :: Python :: 3
Classifier: Operating System :: MacOS :: MacOS X
Classifier: Operating System :: Microsoft :: Windows
Requires-Dist: requests
Requires-Dist: numpy
